perf/__init__.py
perf/_checks.py
perf/_inspect.py
perf/_precision.py
perf/_timing.py
perf/_utils.py
perf/benchmark.py
perf/db.py
perf/benchmarks/__init__.py
perf/benchmarks/fla.py
perf/benchmarks/flash.py
perf/benchmarks/runs.py
perf/benchmarks/sdpa.py
power_attention/__init__.py
power_attention/_config.py
power_attention/_utils.py
power_attention/create_inputs.py
power_attention/cuda.py
power_attention/kernelgen.py
power_attention/power_full.py
power_attention/power_full_maker.py
power_attention/reference.py
power_attention/triton.py
power_attention/vidrial.py
power_attention/vidrial_fused.py
power_attention/vidrial_fused_reference.py
power_attention/vidrial_reference.py
power_attention/_attention/__init__.py
power_attention/_attention/create_inputs.py
power_attention/_attention/cuda.py
power_attention/_attention/reference.py
power_attention/_attention/triton.py
power_attention/_discumsum/__init__.py
power_attention/_discumsum/create_inputs.py
power_attention/_discumsum/cuda.py
power_attention/_discumsum/reference.py
power_attention/_discumsum/triton.py
power_attention/_query_state/__init__.py
power_attention/_query_state/create_inputs.py
power_attention/_query_state/cuda.py
power_attention/_query_state/reference.py
power_attention/_query_state/reference_vidrial.py
power_attention/_query_state/reference_vidrial_fused.py
power_attention/_query_state/triton.py
power_attention/_query_state/vidrial.py
power_attention/_query_state/vidrial_fused.py
power_attention/_query_state/vidrial_fused_kernel.py
power_attention/_update_state/__init__.py
power_attention/_update_state/create_inputs.py
power_attention/_update_state/cuda.py
power_attention/_update_state/reference.py
power_attention/_update_state/reference_vidrial.py
power_attention/_update_state/reference_vidrial_fused.py
power_attention/_update_state/triton.py
power_attention/_update_state/vidrial.py
power_attention/_update_state/vidrial_fused.py
power_attention-1.4.4.dist-info/licenses/LICENSE
power_attention-1.4.4.dist-info/METADATA
power_attention-1.4.4.dist-info/WHEEL
power_attention-1.4.4.dist-info/top_level.txt
power_attention-1.4.4.dist-info/RECORD
