Metadata-Version: 2.4
Name: power-attention
Version: 1.4.4
Summary: Kernels for symmetric-power-based linear transformers
Author-email: Sean Zhang <sean@manifest.com>, Carles Gelada <cgel@manifest.com>, Jacob Buckman <jacob@manifest.com>, Txus Bach <txus@manifest.com>
Classifier: Programming Language :: Python :: 3
Classifier: License :: OSI Approved :: MIT License
Requires-Python: >=3.11
License-File: LICENSE
Requires-Dist: numpy>=2.2
Requires-Dist: torch>=2.6.0
Requires-Dist: triton>=3.2
Requires-Dist: setuptools>=69.5.1
Requires-Dist: einops
Requires-Dist: vidrial==0.1.3
Provides-Extra: dev
Requires-Dist: twine; extra == "dev"
Requires-Dist: pytest>=8.3.4; extra == "dev"
Requires-Dist: pytest-xdist; extra == "dev"
Requires-Dist: cibuildwheel; extra == "dev"
Requires-Dist: auditwheel; extra == "dev"
Requires-Dist: wheel; extra == "dev"
Requires-Dist: build; extra == "dev"
Requires-Dist: tiktoken; extra == "dev"
Requires-Dist: datasets; extra == "dev"
Requires-Dist: httpx; extra == "dev"
Requires-Dist: tqdm; extra == "dev"
Requires-Dist: pytest>=8.3.4; extra == "dev"
Requires-Dist: pytest-xdist; extra == "dev"
Requires-Dist: wheel; extra == "dev"
Requires-Dist: build; extra == "dev"
Requires-Dist: cibuildwheel; extra == "dev"
Requires-Dist: auditwheel; extra == "dev"
Requires-Dist: twine; extra == "dev"
Requires-Dist: click; extra == "dev"
Requires-Dist: pyyaml; extra == "dev"
Requires-Dist: bokeh; extra == "dev"
Requires-Dist: matplotlib; extra == "dev"
Requires-Dist: pymdown-extensions; extra == "dev"
Requires-Dist: mkdocs; extra == "dev"
Requires-Dist: mkdocstrings-python; extra == "dev"
Requires-Dist: requests; extra == "dev"
Requires-Dist: wandb; extra == "dev"
Requires-Dist: zarr; extra == "dev"
Requires-Dist: psutil; extra == "dev"
Requires-Dist: bokeh; extra == "dev"
Requires-Dist: click; extra == "dev"
Requires-Dist: tabulate; extra == "dev"
Requires-Dist: flash-linear-attention; extra == "dev"
Requires-Dist: flash_attn==2.7.3; extra == "dev"
Requires-Dist: pytest-randomly; extra == "dev"
Requires-Dist: pytest-rerunfailures; extra == "dev"
Dynamic: license-file
